sample/__init__.py
sample/package_data.dat
sample/simple.py
sampleproject_dhchenx-0.0.1a2.dist-info/LICENSE.txt
sampleproject_dhchenx-0.0.1a2.dist-info/METADATA
sampleproject_dhchenx-0.0.1a2.dist-info/WHEEL
sampleproject_dhchenx-0.0.1a2.dist-info/top_level.txt
sampleproject_dhchenx-0.0.1a2.dist-info/RECORD
