Metadata-Version: 2.1
Name: sampleproject-dhchenx
Version: 0.0.1a2
Summary: A sample Python project developed by Donghua Chen
Author-email: Donghua Chen <douglaschan@126.com>
License: MIT License
Project-URL: Homepage, https://github.com/dhchenx/sampleproject
Project-URL: Bug Reports, https://github.com/dhchenx/sampleproject/issues
Project-URL: Source, https://github.com/dhchenx/sampleproject/
Keywords: sample,setuptools,development
Classifier: Development Status :: 4 - Beta
Classifier: Intended Audience :: Developers
Classifier: Topic :: Software Development :: Build Tools
Classifier: License :: OSI Approved :: MIT License
Classifier: Programming Language :: Python :: 3
Classifier: Programming Language :: Python :: 3.7
Classifier: Programming Language :: Python :: 3.8
Classifier: Programming Language :: Python :: 3.9
Classifier: Programming Language :: Python :: 3.10
Classifier: Programming Language :: Python :: 3.11
Classifier: Programming Language :: Python :: 3 :: Only
Requires-Python: >=3.7
License-File: LICENSE.txt
Requires-Dist: numpy
Provides-Extra: dev
Requires-Dist: check-manifest ; extra == 'dev'
Provides-Extra: test
Requires-Dist: coverage ; extra == 'test'
